{
  "version": "1",
  "tournament": {
    "id": "tournament-1780251377063",
    "name": "National Basketball League (Men) Division 2 2024",
    "year": 2024,
    "month": "Apr",
    "teamIds": [
      "team-1780252086140",
      "team-kx-div2-amity",
      "team-kx-div2-kts",
      "team-kx-div2-police",
      "team-kx-div2-gmac",
      "team-kx-div2-chong-ghee",
      "team-kx-div2-safsa",
      "team-kx-div2-tungsan",
      "team-kx-div2-loaded",
      "team-kx-div2-tampines-east",
      "team-kx-div2-clementi",
      "team-kx-div2-skc"
    ]
  },
  "teams": [
    {
      "id": "team-1780252086140",
      "name": "Kai Xuan",
      "abbreviation": "KX",
      "currentTournamentId": "tournament-1780251377063",
      "players": []
    },
    {
      "id": "team-kx-div2-amity",
      "name": "Amity",
      "abbreviation": "AMT",
      "currentTournamentId": "tournament-1780251377063",
      "players": []
    },
    {
      "id": "team-kx-div2-kts",
      "name": "KTS",
      "abbreviation": "KTS",
      "currentTournamentId": "tournament-1780251377063",
      "players": []
    },
    {
      "id": "team-kx-div2-police",
      "name": "Police",
      "abbreviation": "POL",
      "currentTournamentId": "tournament-1780251377063",
      "players": []
    },
    {
      "id": "team-kx-div2-gmac",
      "name": "GMAC",
      "abbreviation": "GMAC",
      "currentTournamentId": "tournament-1780251377063",
      "players": []
    },
    {
      "id": "team-kx-div2-chong-ghee",
      "name": "Chong Ghee",
      "abbreviation": "CG",
      "currentTournamentId": "tournament-1780251377063",
      "players": []
    },
    {
      "id": "team-kx-div2-safsa",
      "name": "SAFSA",
      "abbreviation": "SAFSA",
      "currentTournamentId": "tournament-1780251377063",
      "players": []
    },
    {
      "id": "team-kx-div2-tungsan",
      "name": "Tungsan",
      "abbreviation": "TGS",
      "currentTournamentId": "tournament-1780251377063",
      "players": []
    },
    {
      "id": "team-kx-div2-loaded",
      "name": "Loaded",
      "abbreviation": "LOAD",
      "currentTournamentId": "tournament-1780251377063",
      "players": []
    },
    {
      "id": "team-kx-div2-tampines-east",
      "name": "Tampines East",
      "abbreviation": "TPE",
      "currentTournamentId": "tournament-1780251377063",
      "players": []
    },
    {
      "id": "team-kx-div2-clementi",
      "name": "Clementi",
      "abbreviation": "CLEM",
      "currentTournamentId": "tournament-1780251377063",
      "players": []
    },
    {
      "id": "team-kx-div2-skc",
      "name": "SinKee",
      "abbreviation": "SKC",
      "currentTournamentId": "tournament-1780251377063",
      "players": []
    }
  ],
  "game": {
    "id": "game-kx-div2-2024-06-03-tungsan",
    "homeTeamId": "team-1780252086140",
    "awayTeamId": "team-kx-div2-tungsan",
    "tournamentId": "tournament-1780251377063",
    "date": "2024-06-03",
    "currentPeriod": 4,
    "currentGameTime": "00:00",
    "trackBothTeams": false,
    "isActive": false,
    "isCompleted": true,
    "finalScore": {
      "home": 45,
      "away": 87
    },
    "homeStarters": [
      "player-1780304603336",
      "player-1780304627049",
      "player-1780304716969",
      "player-1780304645177",
      "player-1780304739111"
    ],
    "awayStarters": [],
    "gameStats": [
      {
        "playerId": "player-1780304627049",
        "points": 12,
        "fg_made": 6,
        "fg_attempted": 12,
        "three_made": 0,
        "three_attempted": 4,
        "ft_made": 0,
        "ft_attempted": 0,
        "orb": 0,
        "drb": 4,
        "assists": 1,
        "steals": 0,
        "blocks": 0,
        "turnovers": 5,
        "fouls": 0,
        "tech_fouls": 0,
        "unsportsmanlike_fouls": 0,
        "fouls_drawn": 0,
        "blocks_received": 0,
        "plus_minus": 0,
        "minutes_played": 29.833333333333332
      },
      {
        "playerId": "player-1780304603336",
        "points": 8,
        "fg_made": 4,
        "fg_attempted": 15,
        "three_made": 0,
        "three_attempted": 5,
        "ft_made": 0,
        "ft_attempted": 0,
        "orb": 1,
        "drb": 4,
        "assists": 3,
        "steals": 0,
        "blocks": 0,
        "turnovers": 1,
        "fouls": 0,
        "tech_fouls": 0,
        "unsportsmanlike_fouls": 0,
        "fouls_drawn": 0,
        "blocks_received": 0,
        "plus_minus": 0,
        "minutes_played": 32.083333333333336
      },
      {
        "playerId": "player-1780304739111",
        "points": 6,
        "fg_made": 3,
        "fg_attempted": 5,
        "three_made": 0,
        "three_attempted": 0,
        "ft_made": 0,
        "ft_attempted": 2,
        "orb": 0,
        "drb": 2,
        "assists": 0,
        "steals": 0,
        "blocks": 0,
        "turnovers": 3,
        "fouls": 0,
        "tech_fouls": 0,
        "unsportsmanlike_fouls": 0,
        "fouls_drawn": 0,
        "blocks_received": 0,
        "plus_minus": 0,
        "minutes_played": 21.383333333333333
      },
      {
        "playerId": "player-1780304716969",
        "points": 5,
        "fg_made": 2,
        "fg_attempted": 4,
        "three_made": 0,
        "three_attempted": 0,
        "ft_made": 1,
        "ft_attempted": 2,
        "orb": 1,
        "drb": 4,
        "assists": 2,
        "steals": 1,
        "blocks": 2,
        "turnovers": 2,
        "fouls": 3,
        "tech_fouls": 0,
        "unsportsmanlike_fouls": 0,
        "fouls_drawn": 0,
        "blocks_received": 0,
        "plus_minus": 0,
        "minutes_played": 23.8
      },
      {
        "playerId": "player-1780304796452",
        "points": 5,
        "fg_made": 2,
        "fg_attempted": 5,
        "three_made": 1,
        "three_attempted": 4,
        "ft_made": 0,
        "ft_attempted": 0,
        "orb": 0,
        "drb": 1,
        "assists": 1,
        "steals": 0,
        "blocks": 0,
        "turnovers": 0,
        "fouls": 1,
        "tech_fouls": 0,
        "unsportsmanlike_fouls": 0,
        "fouls_drawn": 0,
        "blocks_received": 0,
        "plus_minus": 0,
        "minutes_played": 14.016666666666667
      },
      {
        "playerId": "player-1780304751492",
        "points": 4,
        "fg_made": 2,
        "fg_attempted": 5,
        "three_made": 0,
        "three_attempted": 0,
        "ft_made": 0,
        "ft_attempted": 0,
        "orb": 2,
        "drb": 2,
        "assists": 0,
        "steals": 2,
        "blocks": 0,
        "turnovers": 3,
        "fouls": 0,
        "tech_fouls": 0,
        "unsportsmanlike_fouls": 0,
        "fouls_drawn": 0,
        "blocks_received": 0,
        "plus_minus": 0,
        "minutes_played": 15.866666666666667
      },
      {
        "playerId": "player-sunig-ntu-10",
        "points": 3,
        "fg_made": 1,
        "fg_attempted": 3,
        "three_made": 1,
        "three_attempted": 2,
        "ft_made": 0,
        "ft_attempted": 0,
        "orb": 1,
        "drb": 0,
        "assists": 0,
        "steals": 0,
        "blocks": 0,
        "turnovers": 0,
        "fouls": 1,
        "tech_fouls": 0,
        "unsportsmanlike_fouls": 0,
        "fouls_drawn": 0,
        "blocks_received": 0,
        "plus_minus": 0,
        "minutes_played": 15.783333333333333
      },
      {
        "playerId": "player-1780304645177",
        "points": 2,
        "fg_made": 1,
        "fg_attempted": 5,
        "three_made": 0,
        "three_attempted": 1,
        "ft_made": 0,
        "ft_attempted": 0,
        "orb": 1,
        "drb": 3,
        "assists": 0,
        "steals": 1,
        "blocks": 0,
        "turnovers": 1,
        "fouls": 3,
        "tech_fouls": 0,
        "unsportsmanlike_fouls": 0,
        "fouls_drawn": 0,
        "blocks_received": 0,
        "plus_minus": 0,
        "minutes_played": 23
      },
      {
        "playerId": "player-1780304849666",
        "points": 0,
        "fg_made": 0,
        "fg_attempted": 3,
        "three_made": 0,
        "three_attempted": 0,
        "ft_made": 0,
        "ft_attempted": 0,
        "orb": 1,
        "drb": 1,
        "assists": 0,
        "steals": 1,
        "blocks": 0,
        "turnovers": 0,
        "fouls": 1,
        "tech_fouls": 0,
        "unsportsmanlike_fouls": 0,
        "fouls_drawn": 0,
        "blocks_received": 0,
        "plus_minus": 0,
        "minutes_played": 12.483333333333333
      },
      {
        "playerId": "player-1780304779628",
        "points": 0,
        "fg_made": 0,
        "fg_attempted": 2,
        "three_made": 0,
        "three_attempted": 2,
        "ft_made": 0,
        "ft_attempted": 0,
        "orb": 2,
        "drb": 0,
        "assists": 3,
        "steals": 0,
        "blocks": 0,
        "turnovers": 2,
        "fouls": 1,
        "tech_fouls": 0,
        "unsportsmanlike_fouls": 0,
        "fouls_drawn": 0,
        "blocks_received": 0,
        "plus_minus": 0,
        "minutes_played": 11.75
      }
    ],
    "teamStats": {
      "home": {
        "teamId": "team-1780252086140",
        "q1_points": 0,
        "q2_points": 0,
        "q3_points": 0,
        "q4_points": 0,
        "ot_points": 0,
        "total_points": 45,
        "fg_made": 0,
        "fg_attempted": 0,
        "three_made": 0,
        "three_attempted": 0,
        "ft_made": 0,
        "ft_attempted": 0,
        "orb": 0,
        "drb": 0,
        "assists": 0,
        "steals": 0,
        "blocks": 0,
        "turnovers": 0,
        "fouls": 0
      },
      "away": {
        "teamId": "team-kx-div2-tungsan",
        "q1_points": 0,
        "q2_points": 0,
        "q3_points": 0,
        "q4_points": 0,
        "ot_points": 0,
        "total_points": 87,
        "fg_made": 0,
        "fg_attempted": 0,
        "three_made": 0,
        "three_attempted": 0,
        "ft_made": 0,
        "ft_attempted": 0,
        "orb": 0,
        "drb": 0,
        "assists": 0,
        "steals": 0,
        "blocks": 0,
        "turnovers": 0,
        "fouls": 0
      }
    },
    "shots": [],
    "events": [],
    "lineupStints": []
  }
}
